allogate/__init__.py
allogate-1.0.0.dist-info/LICENSE
allogate-1.0.0.dist-info/METADATA
allogate-1.0.0.dist-info/WHEEL
allogate-1.0.0.dist-info/top_level.txt
allogate-1.0.0.dist-info/RECORD
