Metadata-Version: 2.1
Name: allogate
Version: 1.0.0
Summary: A logging package but very pretty and has stacks and stuff
Home-page: https://github.com/FlameOfIgnis/allogate
Author: Ignis
Author-email: me@ignis.wtf
License: UNKNOWN
Platform: UNKNOWN
Classifier: Programming Language :: Python :: 3
Classifier: License :: OSI Approved :: MIT License
Classifier: Operating System :: OS Independent
Requires-Python: >=3.4
